README.md
setup.py
pulumiverse_harbor/__init__.py
pulumiverse_harbor/_inputs.py
pulumiverse_harbor/_utilities.py
pulumiverse_harbor/config_auth.py
pulumiverse_harbor/config_email.py
pulumiverse_harbor/config_security.py
pulumiverse_harbor/config_system.py
pulumiverse_harbor/garbage_collection.py
pulumiverse_harbor/get_groups.py
pulumiverse_harbor/get_project.py
pulumiverse_harbor/get_project_member_groups.py
pulumiverse_harbor/get_project_member_users.py
pulumiverse_harbor/get_projects.py
pulumiverse_harbor/get_registry.py
pulumiverse_harbor/get_robot_accounts.py
pulumiverse_harbor/get_users.py
pulumiverse_harbor/group.py
pulumiverse_harbor/immutable_tag_rule.py
pulumiverse_harbor/interrogation_services.py
pulumiverse_harbor/label.py
pulumiverse_harbor/outputs.py
pulumiverse_harbor/preheat_instance.py
pulumiverse_harbor/project.py
pulumiverse_harbor/project_member_group.py
pulumiverse_harbor/project_member_user.py
pulumiverse_harbor/project_webhook.py
pulumiverse_harbor/provider.py
pulumiverse_harbor/pulumi-plugin.json
pulumiverse_harbor/purge_audit_log.py
pulumiverse_harbor/py.typed
pulumiverse_harbor/registry.py
pulumiverse_harbor/replication.py
pulumiverse_harbor/retention_policy.py
pulumiverse_harbor/robot_account.py
pulumiverse_harbor/tasks.py
pulumiverse_harbor/user.py
pulumiverse_harbor.egg-info/PKG-INFO
pulumiverse_harbor.egg-info/SOURCES.txt
pulumiverse_harbor.egg-info/dependency_links.txt
pulumiverse_harbor.egg-info/not-zip-safe
pulumiverse_harbor.egg-info/requires.txt
pulumiverse_harbor.egg-info/top_level.txt
pulumiverse_harbor/config/__init__.py
pulumiverse_harbor/config/vars.py