Metadata-Version: 2.1
Name: pulumiverse-harbor
Version: 3.10.21
Summary: A Pulumi package for creating and managing Harbor resources.
Home-page: https://www.pulumi.com
License: Apache-2.0
Project-URL: Repository, https://github.com/pulumiverse/pulumi-harbor
Keywords: pulumi harbor category/utility
Platform: UNKNOWN
Requires-Python: >=3.9
